amock-0.1.1.dist-info/METADATA
amock-0.1.1.dist-info/WHEEL
amock-0.1.1.dist-info/entry_points.txt
amock/__init__.py
amock/main.py
amock/prompt.py
amock-0.1.1.dist-info/RECORD
